LICENSE
MANIFEST.in
README.md
setup.py
django_test_helper.egg-info/PKG-INFO
django_test_helper.egg-info/SOURCES.txt
django_test_helper.egg-info/dependency_links.txt
django_test_helper.egg-info/requires.txt
django_test_helper.egg-info/top_level.txt
test_helper/__init__.py
test_helper/utils.py