Metadata-Version: 1.0
Name: django-test-helper
Version: 0.1a2
Summary: Utilites for Django tests.
Home-page: https://bitbucket.org/nextscreenlabs/django-test-helper
Author: Jason Christa
Author-email: jason@zeitcode.com
License: UNKNOWN
Platform: UNKNOWN
Classifier: Environment :: Web Environment
Classifier: License :: OSI Approved :: BSD License
Classifier: Framework :: Django
Classifier: Programming Language :: Python
